gkdbnf/__init__.py
gkdbnf/bnflexer.py
gkdbnf/bnfparse.py
gkdbnf/cli.py
gkdbnf/wrap.py
gkdbnf-0.4.2.dist-info/LICENSE
gkdbnf-0.4.2.dist-info/METADATA
gkdbnf-0.4.2.dist-info/WHEEL
gkdbnf-0.4.2.dist-info/entry_points.txt
gkdbnf-0.4.2.dist-info/top_level.txt
gkdbnf-0.4.2.dist-info/RECORD
