Metadata-Version: 2.1
Name: gkdbnf
Version: 0.4.2
Summary: UNKNOWN
Home-page: https://github.com/thautwarm/gkdbnf
Author: thautwarm
Author-email: twshere@outlook.com
License: mit
Keywords: LaTex,BNF
Platform: any
Classifier: Programming Language :: Python :: 3.7
Classifier: Programming Language :: Python :: 3.8
Classifier: Programming Language :: Python :: Implementation :: CPython
Requires-Python: >=3.7.0
Requires-Dist: wisepy2 (>=1.0)
Requires-Dist: gkdtex (>=0.2)
